autogluon.eda-0.8.3-py3.8-nspkg.pth
autogluon/eda/__init__.py
autogluon/eda/state.py
autogluon/eda/version.py
autogluon/eda/analysis/__init__.py
autogluon/eda/analysis/anomaly.py
autogluon/eda/analysis/base.py
autogluon/eda/analysis/dataset.py
autogluon/eda/analysis/explain.py
autogluon/eda/analysis/interaction.py
autogluon/eda/analysis/missing.py
autogluon/eda/analysis/model.py
autogluon/eda/analysis/shift.py
autogluon/eda/analysis/transform.py
autogluon/eda/auto/__init__.py
autogluon/eda/auto/simple.py
autogluon/eda/utils/__init__.py
autogluon/eda/utils/common.py
autogluon/eda/utils/defaults.py
autogluon/eda/visualization/__init__.py
autogluon/eda/visualization/anomaly.py
autogluon/eda/visualization/base.py
autogluon/eda/visualization/dataset.py
autogluon/eda/visualization/explain.py
autogluon/eda/visualization/interaction.py
autogluon/eda/visualization/jupyter.py
autogluon/eda/visualization/layouts.py
autogluon/eda/visualization/missing.py
autogluon/eda/visualization/model.py
autogluon/eda/visualization/shift.py
autogluon.eda-0.8.3.dist-info/LICENSE
autogluon.eda-0.8.3.dist-info/METADATA
autogluon.eda-0.8.3.dist-info/NOTICE
autogluon.eda-0.8.3.dist-info/WHEEL
autogluon.eda-0.8.3.dist-info/namespace_packages.txt
autogluon.eda-0.8.3.dist-info/top_level.txt
autogluon.eda-0.8.3.dist-info/zip-safe
autogluon.eda-0.8.3.dist-info/RECORD
