Metadata-Version: 2.1
Name: autogluon.eda
Version: 0.8.3
Summary: AutoML for Image, Text, and Tabular Data
Home-page: https://github.com/autogluon/autogluon
Author: AutoGluon Community
License: Apache-2.0
Project-URL: Documentation, https://auto.gluon.ai
Project-URL: Bug Reports, https://github.com/autogluon/autogluon/issues
Project-URL: Source, https://github.com/autogluon/autogluon/
Project-URL: Contribute!, https://github.com/autogluon/autogluon/blob/master/CONTRIBUTING.md
Platform: UNKNOWN
Classifier: Development Status :: 4 - Beta
Classifier: Intended Audience :: Education
Classifier: Intended Audience :: Developers
Classifier: Intended Audience :: Science/Research
Classifier: Intended Audience :: Customer Service
Classifier: Intended Audience :: Financial and Insurance Industry
Classifier: Intended Audience :: Healthcare Industry
Classifier: Intended Audience :: Telecommunications Industry
Classifier: License :: OSI Approved :: Apache Software License
Classifier: Operating System :: MacOS
Classifier: Operating System :: Microsoft :: Windows
Classifier: Operating System :: POSIX
Classifier: Operating System :: Unix
Classifier: Programming Language :: Python :: 3
Classifier: Programming Language :: Python :: 3.8
Classifier: Programming Language :: Python :: 3.9
Classifier: Programming Language :: Python :: 3.10
Classifier: Topic :: Software Development
Classifier: Topic :: Scientific/Engineering :: Artificial Intelligence
Classifier: Topic :: Scientific/Engineering :: Information Analysis
Classifier: Topic :: Scientific/Engineering :: Image Recognition
Requires-Python: >=3.8, <3.11
Requires-Dist: numpy <1.27,>=1.21
Requires-Dist: scipy <1.12,>=1.5.4
Requires-Dist: scikit-learn <1.4.1,>=1.1
Requires-Dist: pandas <1.6,>=1.4.1
Requires-Dist: matplotlib <3.7,>=3.4
Requires-Dist: missingno <0.6,>=0.5.1
Requires-Dist: phik <0.13,>=0.12.2
Requires-Dist: seaborn <0.13,>=0.12.0
Requires-Dist: ipywidgets <9.0,>=7.7.1
Requires-Dist: shap <0.42,>=0.41
Requires-Dist: yellowbrick <1.6,>=1.5
Requires-Dist: pyod <1.1,>=1.0
Requires-Dist: suod <0.1,>=0.0.8
Requires-Dist: ipython <8.13,>7.16
Requires-Dist: autogluon.core ==0.8.3
Requires-Dist: autogluon.common ==0.8.3
Requires-Dist: autogluon.features ==0.8.3
Requires-Dist: autogluon.tabular ==0.8.3
Provides-Extra: tests
Requires-Dist: pytest ; extra == 'tests'
Requires-Dist: tox ; extra == 'tests'
Requires-Dist: PyHamcrest ; extra == 'tests'
Requires-Dist: pytest-cov ; extra == 'tests'
Requires-Dist: isort ; extra == 'tests'
Requires-Dist: types-requests ; extra == 'tests'
Requires-Dist: types-setuptools ; extra == 'tests'
Requires-Dist: pytest-mypy ; extra == 'tests'
